pyfsdb_parquet/__init__.py
pyfsdb_parquet/parquet/__init__.py
pyfsdb_parquet/tools/__init__.py
pyfsdb_parquet/tools/fsdb2parquet.py
pyfsdb_parquet/tools/parquet2fsdb.py
pyfsdb_parquet-1.0.2.dist-info/METADATA
pyfsdb_parquet-1.0.2.dist-info/WHEEL
pyfsdb_parquet-1.0.2.dist-info/entry_points.txt
pyfsdb_parquet-1.0.2.dist-info/top_level.txt
pyfsdb_parquet-1.0.2.dist-info/RECORD
