Metadata-Version: 2.1
Name: pyfsdb-parquet
Version: 1.0.2
Summary: Python tools to convert to and from FSDB and parquet files
Home-page: https://github.com/gawseed/pyfsdb_parquet
Author: Wes Hardaker
Author-email: opensource@hardakers.net
License: UNKNOWN
Platform: UNKNOWN
Classifier: Programming Language :: Python :: 3
Classifier: Operating System :: OS Independent
Requires-Python: >=3.6
Requires-Dist: pyfsdb (>=2.0.3)
Requires-Dist: cramjam
Requires-Dist: pandas
Requires-Dist: fastparquet
Requires-Dist: pyarrow
